PuaWanhui/README.md
PuaWanhui/__init__.py
PuaWanhui/__main__.py
PuaWanhui/file.epub
PuaWanhui/index.html
PuaWanhui/css/__init__.py
PuaWanhui/css/annotations.css
PuaWanhui/css/main.css
PuaWanhui/css/normalize.css
PuaWanhui/css/popup.css
PuaWanhui/font/__init__.py
PuaWanhui/font/fontello.eot
PuaWanhui/font/fontello.svg
PuaWanhui/font/fontello.ttf
PuaWanhui/font/fontello.woff
PuaWanhui/img/__init__.py
PuaWanhui/img/annotator-glyph-sprite.png
PuaWanhui/img/annotator-icon-sprite.png
PuaWanhui/img/apple-touch-icon.png
PuaWanhui/img/cancelfullscreen.png
PuaWanhui/img/close.png
PuaWanhui/img/fullscreen.png
PuaWanhui/img/loader.gif
PuaWanhui/img/menu-icon.png
PuaWanhui/img/save.png
PuaWanhui/img/saved.png
PuaWanhui/img/settings-s.png
PuaWanhui/img/settings.png
PuaWanhui/img/star.png
PuaWanhui/js/__init__.py
PuaWanhui/js/epub.js
PuaWanhui/js/epub.min.js
PuaWanhui/js/epub.min.map
PuaWanhui/js/hooks.min.js
PuaWanhui/js/hooks.min.map
PuaWanhui/js/reader.js
PuaWanhui/js/reader.js.map
PuaWanhui/js/reader.min.js
PuaWanhui/js/reader.min.map
PuaWanhui/js/hooks/__init__.py
PuaWanhui/js/hooks/extensions/__init__.py
PuaWanhui/js/hooks/extensions/highlight.js
PuaWanhui/js/libs/__init__.py
PuaWanhui/js/libs/jquery.min.js
PuaWanhui/js/libs/localforage.min.js
PuaWanhui/js/libs/screenfull.js
PuaWanhui/js/libs/screenfull.min.js
PuaWanhui/js/libs/zip.min.js
PuaWanhui/js/plugins/__init__.py
PuaWanhui/js/plugins/hypothesis.js
PuaWanhui/js/plugins/search.js
pua_wanhui-2022.10.11.0.dist-info/METADATA
pua_wanhui-2022.10.11.0.dist-info/WHEEL
pua_wanhui-2022.10.11.0.dist-info/entry_points.txt
pua_wanhui-2022.10.11.0.dist-info/top_level.txt
pua_wanhui-2022.10.11.0.dist-info/RECORD
